pyimfit/config.py
pyimfit/imfit_funcs.py
pyimfit/__init__.py
pyimfit/psf.py
pyimfit/utils.py
pyimfit/fitting.py
pyimfit/pyimfit_lib.cpython-312-darwin.so
pyimfit/descriptions.py
pyimfit/tests/test_oversampled_psf.py
pyimfit/tests/test_descriptions.py
pyimfit/tests/test_imfit.py
pyimfit/tests/__init__.py
pyimfit/tests/test_fits_and_fitstatistics.py
pyimfit/tests/test_temp.py
pyimfit/tests/test_fitting.py
pyimfit/tests/old_test_model.py
pyimfit/tests/test_config.py
pyimfit/tests/test_bootstrap.py
pyimfit-1.1.dist-info/RECORD
pyimfit-1.1.dist-info/WHEEL
pyimfit-1.1.dist-info/top_level.txt
pyimfit-1.1.dist-info/LICENSE.txt
pyimfit-1.1.dist-info/METADATA
