Metadata-Version: 2.1
Name: pyimfit
Version: 1.1
Summary: Python wrapper for astronomical image-fitting program Imfit
Home-page: https://github.com/perwin/pyimfit
Author: Peter Erwin
Author-email: peter.erwin@gmail.com
Project-URL: Documentation, https://pyimfit.readthedocs.io/en/latest/
Project-URL: Source, https://github.com/perwin/pyimfit
Classifier: Programming Language :: Python :: 3
Classifier: Programming Language :: Cython
Classifier: Programming Language :: C++
Classifier: License :: OSI Approved :: GNU General Public License v3 (GPLv3)
Classifier: Operating System :: POSIX
Classifier: Intended Audience :: Science/Research
Requires-Python: >=3.10
License-File: LICENSE.txt
Requires-Dist: numpy
Requires-Dist: scipy
